MANIFEST.in
README.rst
setup.py
docs/HISTORY.txt
docs/INSTALL.txt
docs/LICENSE.GPL
docs/LICENSE.txt
ftw/__init__.py
ftw.usermigration.egg-info/PKG-INFO
ftw.usermigration.egg-info/SOURCES.txt
ftw.usermigration.egg-info/dependency_links.txt
ftw.usermigration.egg-info/entry_points.txt
ftw.usermigration.egg-info/namespace_packages.txt
ftw.usermigration.egg-info/not-zip-safe
ftw.usermigration.egg-info/requires.txt
ftw.usermigration.egg-info/top_level.txt
ftw/usermigration/__init__.py
ftw/usermigration/configure.zcml
ftw/usermigration/dashboard.py
ftw/usermigration/globalroles.py
ftw/usermigration/group_members.py
ftw/usermigration/homefolder.py
ftw/usermigration/interfaces.py
ftw/usermigration/localroles.py
ftw/usermigration/loginnames.py
ftw/usermigration/properties.py
ftw/usermigration/testing.py
ftw/usermigration/userids.py
ftw/usermigration/utils.py
ftw/usermigration/vocabularies.py
ftw/usermigration/browser/__init__.py
ftw/usermigration/browser/configure.zcml
ftw/usermigration/browser/migration.pt
ftw/usermigration/browser/migration.py
ftw/usermigration/browser/migration_summary.pt
ftw/usermigration/tests/__init__.py
ftw/usermigration/tests/test_dashboard.py
ftw/usermigration/tests/test_globalroles.py
ftw/usermigration/tests/test_group_members.py
ftw/usermigration/tests/test_homefolder.py
ftw/usermigration/tests/test_localroles.py
ftw/usermigration/tests/test_loginnames.py
ftw/usermigration/tests/test_migration_form.py
ftw/usermigration/tests/test_properties.py
ftw/usermigration/tests/test_userids.py