Metadata-Version: 2.1
Name: ftw.usermigration
Version: 1.3.0
Summary: User migration for Plone
Home-page: https://github.com/4teamwork/ftw.usermigration
Author: Thomas Buchberger
Author-email: t.buchberger@4teamwork.ch
License: GPL
Platform: UNKNOWN
Classifier: Framework :: Plone
Classifier: Framework :: Plone :: 4.3
Classifier: Framework :: Plone :: 5.1
Classifier: Framework :: Plone :: 5.2
Classifier: Programming Language :: Python
Classifier: Programming Language :: Python :: 3.8
Provides-Extra: tests
